byted_overpass_life_alliance_task_fulfilment_base/__init__.py
byted_overpass_life_alliance_task_fulfilment_base-0.0.1.dist-info/METADATA
byted_overpass_life_alliance_task_fulfilment_base-0.0.1.dist-info/WHEEL
byted_overpass_life_alliance_task_fulfilment_base-0.0.1.dist-info/top_level.txt
byted_overpass_life_alliance_task_fulfilment_base-0.0.1.dist-info/RECORD
